meu_projeto_139/__init__.py
meu_projeto_139/meu_projeto.py
meu_projeto_139-0.1.0.dist-info/METADATA
meu_projeto_139-0.1.0.dist-info/WHEEL
meu_projeto_139-0.1.0.dist-info/RECORD
