Metadata-Version: 2.1
Name: meu-projeto-139
Version: 0.1.0
Summary: Uma breve descrição do seu projeto.
Author: Wagner Santos
Author-email: rengaw.luiz@gmail.com
Requires-Python: >=3.10,<4.0
Classifier: Programming Language :: Python :: 3
Classifier: Programming Language :: Python :: 3.10
Classifier: Programming Language :: Python :: 3.11
Classifier: Programming Language :: Python :: 3.12
